Metadata-Version: 1.2
Name: livelex-qt
Version: 0.3.0
Summary: The livelexqt Python module
Home-page: https://github.com/wbsoft/livelex-qt
Maintainer: Wilbert Berendsen
Maintainer-email: info@wilbertberendsen.nl
License: GPL
Platform: UNKNOWN
Classifier: Development Status :: 3 - Alpha
Classifier: Intended Audience :: Developers
Classifier: License :: OSI Approved :: GNU General Public License v3 or later (GPLv3+)
Classifier: Programming Language :: Python :: 3.3
Classifier: Topic :: Text Processing
Classifier: Environment :: X11 Applications :: Qt
